torch_ivf/__init__.py
torch_ivf/index/__init__.py
torch_ivf/index/base.py
torch_ivf/index/flat.py
torch_ivf/index/ivf_flat.py
torch_ivf/nn/__init__.py
torch_ivf/nn/kmeans.py
torch_ivf/utils/__init__.py
torch_ivf-0.1.1.dist-info/licenses/LICENSE
torch_ivf-0.1.1.dist-info/METADATA
torch_ivf-0.1.1.dist-info/WHEEL
torch_ivf-0.1.1.dist-info/top_level.txt
torch_ivf-0.1.1.dist-info/RECORD
