Metadata-Version: 2.4
Name: torch-ivf
Version: 0.1.1
Summary: PyTorch-native IVF index for CUDA/ROCm/DirectML/CPU.
Author-email: Naruhide KITADA <kitfactory@gmail.com>
License: MIT
Requires-Python: >=3.12
License-File: LICENSE
Provides-Extra: pytorch
Requires-Dist: torch>=2.2; extra == "pytorch"
Dynamic: license-file
